snowy/__init__.py
snowy/color.py
snowy/distance.py
snowy/draw.py
snowy/filtering.py
snowy/io.py
snowy/lighting.py
snowy/noise.py
snowy/ops.py
snowy-0.0.9.dist-info/LICENSE
snowy-0.0.9.dist-info/METADATA
snowy-0.0.9.dist-info/WHEEL
snowy-0.0.9.dist-info/top_level.txt
snowy-0.0.9.dist-info/RECORD
