Metadata-Version: 2.1
Name: snowy
Version: 0.0.9
Summary: Small Image Library for Python 3
Home-page: https://github.com/prideout/snowy
Author: Philip Rideout
License: UNKNOWN
Platform: UNKNOWN
Classifier: Programming Language :: Python :: 3
Classifier: License :: OSI Approved :: MIT License
Classifier: Operating System :: OS Independent
Requires-Python: >=3.6
Requires-Dist: imageio (>=2.3)
Requires-Dist: numpy (>=1.14)
Requires-Dist: numba (>=0.39)
Requires-Dist: scipy (>=0.16)
